brythonserver/__init__.py
brythonserver/__version__.py
brythonserver/definitions.py
brythonserver/main.py
brythonserver/reverseproxied.py
brythonserver/utility.py
brythonserver/static/bs.js
brythonserver/static/bssite.css
brythonserver/static/drive_16dp.png
brythonserver/static/drive_24dp.png
brythonserver/static/drive_32dp.png
brythonserver/static/drive_48dp.png
brythonserver/static/drive_64dp.png
brythonserver/static/favicon-16x16.png
brythonserver/static/favicon-32x32.png
brythonserver/static/favicon-96x96.png
brythonserver/static/favicon.ico
brythonserver/static/brython/README.txt
brythonserver/static/brython/brython.js
brythonserver/static/brython/brython_stdlib.js
brythonserver/static/brython/demo.html
brythonserver/static/brython/index.html
brythonserver/static/brython/unicode.txt
brythonserver/static/brythonserver/__init__.py
brythonserver/static/brythonserver/turtle.py
brythonserver/templates/_rawcookies.html
brythonserver/templates/_rawprivacy.html
brythonserver/templates/_rawtermsofservice.html
brythonserver/templates/console.html
brythonserver/templates/cookiebanner.html
brythonserver/templates/cookies.html
brythonserver/templates/exec.html
brythonserver/templates/index.html
brythonserver/templates/layout.html
brythonserver/templates/legalese.html
brythonserver/templates/privacy.html
brythonserver/templates/termsofservice.html
brython_server-2.3.3.dist-info/METADATA
brython_server-2.3.3.dist-info/WHEEL
brython_server-2.3.3.dist-info/top_level.txt
brython_server-2.3.3.dist-info/RECORD
