Metadata-Version: 2.1
Name: brython-server
Version: 2.3.3
Summary: Simple web based Python 3 IDE with Brython and Github integration
Home-page: https://github.com/tiggerntatie/brython-server
Author: Eric Dennison
Author-email: ericd@netdenizen.com
Classifier: Programming Language :: Python :: 3
Classifier: License :: OSI Approved :: MIT License
Classifier: Operating System :: OS Independent
Requires-Python: >=3.11
Requires-Dist: gunicorn ==19.9.0
Requires-Dist: Flask ==2.1.2
Requires-Dist: werkzeug ==2.1.2
Requires-Dist: pillow ==10.2.0
Requires-Dist: ggame ==1.1.3
